itest/Config.py
itest/__init__.py
itest/core.py
itest/log.py
itest/main.py
itest/static/echarts.common.min.js
itest/static/echarts.simple.min.js
itest/static/index.js
itest/static/index.min.js
itest/static/jquery-3.1.0.min.js
itest/static/mypage.css
itest/static/bootstrap/css/bootstrap-theme.css
itest/static/bootstrap/css/bootstrap-theme.css.map
itest/static/bootstrap/css/bootstrap-theme.min.css
itest/static/bootstrap/css/bootstrap-theme.min.css.map
itest/static/bootstrap/css/bootstrap.css
itest/static/bootstrap/css/bootstrap.css.map
itest/static/bootstrap/css/bootstrap.min.css
itest/static/bootstrap/css/bootstrap.min.css.map
itest/static/bootstrap/fonts/glyphicons-halflings-regular.eot
itest/static/bootstrap/fonts/glyphicons-halflings-regular.svg
itest/static/bootstrap/fonts/glyphicons-halflings-regular.ttf
itest/static/bootstrap/fonts/glyphicons-halflings-regular.woff
itest/static/bootstrap/fonts/glyphicons-halflings-regular.woff2
itest/static/bootstrap/js/bootstrap.js
itest/static/bootstrap/js/bootstrap.min.js
itest/static/bootstrap/js/npm.js
itest/static/datatables/dataTables.bootstrap.css
itest/static/datatables/dataTables.bootstrap.js
itest/static/datatables/dataTables.bootstrap.min.js
itest/static/datatables/jquery.dataTables.css
itest/static/datatables/jquery.dataTables.js
itest/static/datatables/jquery.dataTables.min.css
itest/static/datatables/jquery.dataTables.min.js
itest/static/datatables/jquery.dataTables_themeroller.css
itest/static/datatables/images/sort_asc.png
itest/static/datatables/images/sort_asc_disabled.png
itest/static/datatables/images/sort_both.png
itest/static/datatables/images/sort_desc.png
itest/static/datatables/images/sort_desc_disabled.png
itest/static/img/logo.png
itest/static/img/report.png
itest/static/img/title.png
itest/template/index.html.template
itest/template/testcase.xlsx
itest-1.2.1.dist-info/DESCRIPTION.rst
itest-1.2.1.dist-info/METADATA
itest-1.2.1.dist-info/RECORD
itest-1.2.1.dist-info/WHEEL
itest-1.2.1.dist-info/entry_points.txt
itest-1.2.1.dist-info/metadata.json
itest-1.2.1.dist-info/top_level.txt
